sec_edgar_smolagents/__init__.py
sec_edgar_smolagents/agent.py
sec_edgar_smolagents/mcp_client.py
sec_edgar_smolagents/tools.py
sec_edgar_agentkit_smolagents-0.1.0.dist-info/LICENSE
sec_edgar_agentkit_smolagents-0.1.0.dist-info/METADATA
sec_edgar_agentkit_smolagents-0.1.0.dist-info/WHEEL
sec_edgar_agentkit_smolagents-0.1.0.dist-info/RECORD
