Metadata-Version: 2.3
Name: sec-edgar-agentkit-smolagents
Version: 0.1.0
Summary: SEC EDGAR agentkit for Hugging Face smolagents framework
License: AGPL-3.0
Keywords: sec,edgar,smolagents,huggingface,agent,financial
Author: Stefano Amorelli
Author-email: stefano@amorelli.tech
Requires-Python: >=3.8,<4.0
Classifier: License :: OSI Approved :: GNU Affero General Public License v3
Classifier: Programming Language :: Python :: 3
Classifier: Programming Language :: Python :: 3.8
Classifier: Programming Language :: Python :: 3.9
Classifier: Programming Language :: Python :: 3.10
Classifier: Programming Language :: Python :: 3.11
Classifier: Programming Language :: Python :: 3.12
Classifier: Programming Language :: Python :: 3.13
Requires-Dist: sec-edgar-mcp (>=0.1.0,<0.2.0)
Requires-Dist: smolagents (>=0.1.0,<0.2.0)
Project-URL: Homepage, https://github.com/stefanoamorelli/sec-edgar-agentkit
Project-URL: Repository, https://github.com/stefanoamorelli/sec-edgar-agentkit
